setup.cfg
setup.py
eubh_dev.egg-info/PKG-INFO
eubh_dev.egg-info/SOURCES.txt
eubh_dev.egg-info/dependency_links.txt
eubh_dev.egg-info/entry_points.txt
eubh_dev.egg-info/requires.txt
eubh_dev.egg-info/top_level.txt
eubh_dev.egg-info/zip-safe
src/__init__.py
src/__main__.py
src/eubh/__init__.py
src/eubh/api.py
src/eubh/config.py
src/eubh/get.py
src/eubh/init.py
src/eubh/put.py
src/eubh/status.py
src/eubh/utils.py
src/eubh/watch.py
src/eubh/logs/__init__.py
src/eubh/logs/container_log.py
src/eubh/wesockets/__init__.py
src/eubh/wesockets/container_log.py