Metadata-Version: 1.0
Name: eubh-dev
Version: 0.0.46
Summary: eub client help
Home-page: UNKNOWN
Author: eubchain
Author-email: service@eubchain.com
License: UNKNOWN
Keywords: eub client help
Platform: UNKNOWN
